LICENSE
MANIFEST.in
README.rst
setup.py
django_ohm2_handlers.egg-info/PKG-INFO
django_ohm2_handlers.egg-info/SOURCES.txt
django_ohm2_handlers.egg-info/dependency_links.txt
django_ohm2_handlers.egg-info/top_level.txt
docs/INFO.txt
ohm2_handlers/__init__.py
ohm2_handlers/admin.py
ohm2_handlers/apis.py
ohm2_handlers/apisdispatcher.py
ohm2_handlers/apps.py
ohm2_handlers/context_processors.py
ohm2_handlers/decorators.py
ohm2_handlers/definitions.py
ohm2_handlers/errors.py
ohm2_handlers/managers.py
ohm2_handlers/middlewares.py
ohm2_handlers/models.py
ohm2_handlers/settings.py
ohm2_handlers/tests.py
ohm2_handlers/urls.py
ohm2_handlers/utils.py
ohm2_handlers/views.py
ohm2_handlers/accounts/.DS_Store
ohm2_handlers/accounts/__init__.py
ohm2_handlers/accounts/admin.py
ohm2_handlers/accounts/apis.py
ohm2_handlers/accounts/apisdispatcher.py
ohm2_handlers/accounts/apps.py
ohm2_handlers/accounts/context_processors.py
ohm2_handlers/accounts/decorators.py
ohm2_handlers/accounts/definitions.py
ohm2_handlers/accounts/errors.py
ohm2_handlers/accounts/managers.py
ohm2_handlers/accounts/middlewares.py
ohm2_handlers/accounts/models.py
ohm2_handlers/accounts/serializers.py
ohm2_handlers/accounts/settings.py
ohm2_handlers/accounts/tasks.py
ohm2_handlers/accounts/tests.py
ohm2_handlers/accounts/tests_old.py
ohm2_handlers/accounts/urls.py
ohm2_handlers/accounts/utils.py
ohm2_handlers/accounts/views.py
ohm2_handlers/accounts/viewsdispatcher.py
ohm2_handlers/accounts/__pycache__/__init__.cpython-35.pyc
ohm2_handlers/accounts/__pycache__/admin.cpython-35.pyc
ohm2_handlers/accounts/__pycache__/apis.cpython-35.pyc
ohm2_handlers/accounts/__pycache__/apisdispatcher.cpython-35.pyc
ohm2_handlers/accounts/__pycache__/decorators.cpython-35.pyc
ohm2_handlers/accounts/__pycache__/definitions.cpython-35.pyc
ohm2_handlers/accounts/__pycache__/errors.cpython-35.pyc
ohm2_handlers/accounts/__pycache__/managers.cpython-35.pyc
ohm2_handlers/accounts/__pycache__/models.cpython-35.pyc
ohm2_handlers/accounts/__pycache__/serializers.cpython-35.pyc
ohm2_handlers/accounts/__pycache__/settings.cpython-35.pyc
ohm2_handlers/accounts/__pycache__/tests.cpython-35.pyc
